osintgraph/__init__.py
osintgraph/__main__.py
osintgraph/cli.py
osintgraph/constants.py
osintgraph/credential_manager.py
osintgraph/get_session.py
osintgraph/insta_manager.py
osintgraph/logger.py
osintgraph/neo4j_manager.py
osintgraph/ui.py
osintgraph/osintgraph_agent/__init__.py
osintgraph/osintgraph_agent/osint_graph_agent.py
osintgraph/osintgraph_agent/osint_prompts/__init__.py
osintgraph/osintgraph_agent/osint_prompts/agent_prompts.py
osintgraph/osintgraph_agent/osint_prompts/memory_prompts.py
osintgraph/osintgraph_agent/osint_tools/__init__.py
osintgraph/osintgraph_agent/osint_tools/neo4j_tools.py
osintgraph/osintgraph_agent/osint_tools/template_tools.py
osintgraph/osintgraph_agent/osint_utils/__init__.py
osintgraph/osintgraph_agent/osint_utils/summary_generators.py
osintgraph/services/llm_analyzer.py
osintgraph/services/llm_models.py
osintgraph/utils/data_extractors.py
osintgraph/utils/fetch_urls.py
osintgraph/utils/iso_parser.py
osintgraph/utils/monkey_patches.py
osintgraph/utils/prompts.py
osintgraph/utils/schemas.py
osintgraph-0.1.1.dist-info/METADATA
osintgraph-0.1.1.dist-info/WHEEL
osintgraph-0.1.1.dist-info/entry_points.txt
osintgraph-0.1.1.dist-info/licenses/LICENSE
osintgraph-0.1.1.dist-info/RECORD
