Metadata-Version: 2.4
Name: osintgraph
Version: 0.1.1
Summary: Osintgraph is a tool that maps Instagram targets, revealing social connections, posts, and interactions for OSINT investigations.
Project-URL: Homepage, https://github.com/XD-MHLOO/Osintgraph
Project-URL: Repository, https://github.com/XD-MHLOO/Osintgraph
Author: XD-MHLOO
License-Expression: GPL-3.0-or-later
License-File: LICENSE
Keywords: Instagram,LangChain,LangGraph,Neo4j,OSINT,Social Network Analysis
Requires-Python: >=3.9
Requires-Dist: instaloader==4.14.2
Requires-Dist: langchain-core==0.3.72
Requires-Dist: langchain-google-genai==2.1.8
Requires-Dist: langchain==0.3.27
Requires-Dist: langgraph==0.6.2
Requires-Dist: langmem==0.0.29
Requires-Dist: neo4j==5.28.1
Requires-Dist: platformdirs>=4.0.0
Requires-Dist: protobuf==6.31.1
Requires-Dist: pydantic==2.11.7
Requires-Dist: python-dateutil==2.9.0.post0
Requires-Dist: pyyaml==6.0.2
Requires-Dist: rich==14.1.0
Requires-Dist: tqdm==4.67.1
Requires-Dist: typing-extensions==4.14.1
